AoikPourTable-0.1.0.dist-info/DESCRIPTION.rst
AoikPourTable-0.1.0.dist-info/METADATA
AoikPourTable-0.1.0.dist-info/RECORD
AoikPourTable-0.1.0.dist-info/WHEEL
AoikPourTable-0.1.0.dist-info/entry_points.txt
AoikPourTable-0.1.0.dist-info/metadata.json
AoikPourTable-0.1.0.dist-info/top_level.txt
aoikpourtable/__init__.py
aoikpourtable/__main__.py
aoikpourtable/aoikimportutil.py
aoikpourtable/aoikpourtable.py
aoikpourtable/convert_io.py
aoikpourtable/count_io.py
aoikpourtable/csv_io.py
aoikpourtable/db_io.py
aoikpourtable/empty_io.py
aoikpourtable/main.py
aoikpourtable/print_util.py
aoikpourtable/std_io.py
aoikpourtable/uri_util.py
